django_settings_cmd
