Metadata-Version: 1.1
Name: django-settings-cmd
Version: 0.3
Summary: A commmand line tool to manage the django settings file
Home-page: https://github.com/RubenNorgaard/django-settings-cmd
Author: Ruben Nørgaard
Author-email: email@rubennoergaard.dk
License: UNKNOWN
Download-URL: https://github.com/RubenNorgaard/django-settings-cmd/archive/0.3.tar.gz
Keywords: django,settings,commandline
Platform: UNKNOWN
